{
    "data_format": 1,
    "data_updated": "20240113T080855Z",
    "project": {
        "contact_email": "zkir@zkir.ru",
        "contact_name": "Kirill B. aka Zkir",
        "description": "OSM-based map of Earth land covers",
        "name": "OpenLandcoverMap ;)",
        "project_url": "https://github.com/Zkir/generalized_landcovers"
    },
    "tags": [
        {
            "description": "Rendered as landcover. Strength 13.5, Total count 121676",
            "key": "natural",
            "object_types": [
                "area"
            ],
            "value": "glacier"
        },
        {
            "description": "Rendered as landcover. Strength 13.1, Total count 685091",
            "key": "natural",
            "object_types": [
                "area"
            ],
            "value": "wood"
        },
        {
            "description": "Rendered as landcover. Strength 12.6, Total count 125304",
            "key": "natural",
            "object_types": [
                "area"
            ],
            "value": "desert"
        },
        {
            "description": "Rendered as landcover. Strength 12.6, Total count 38004",
            "key": "natural",
            "object_types": [
                "area"
            ],
            "value": "bare_rock"
        },
        {
            "description": "Rendered as landcover. Strength 12.1, Total count 149385",
            "key": "landuse",
            "object_types": [
                "area"
            ],
            "value": "farmland"
        },
        {
            "description": "Rendered as landcover. Strength 11.8, Total count 89639",
            "key": "natural",
            "object_types": [
                "area"
            ],
            "value": "sand"
        },
        {
            "description": "Rendered as landcover. Strength 11.6, Total count 1229",
            "key": "natural",
            "object_types": [
                "area"
            ],
            "value": "tundra"
        },
        {
            "description": "Rendered as landcover. Strength 11.2, Total count 76554",
            "key": "natural",
            "object_types": [
                "area"
            ],
            "value": "wetland"
        },
        {
            "description": "Accepted as landcover, but not rendered. Strength: 11.1, Total count: 1406",
            "key": "natural",
            "object_types": [
                "area"
            ],
            "value": "dry_lake"
        },
        {
            "description": "Rendered as landcover. Strength 11.0, Total count 15201",
            "key": "landuse",
            "object_types": [
                "area"
            ],
            "value": "meadow"
        },
        {
            "description": "Rendered as landcover. Strength 10.9, Total count 34855",
            "key": "natural",
            "object_types": [
                "area"
            ],
            "value": "scrub"
        },
        {
            "description": "Rendered as landcover. Strength 10.9, Total count 141",
            "key": "natural",
            "object_types": [
                "area"
            ],
            "value": "arctic_desert"
        },
        {
            "description": "Rendered as landcover. Strength 10.8, Total count 8501",
            "key": "natural",
            "object_types": [
                "area"
            ],
            "value": "heath"
        },
        {
            "description": "Rendered as landcover. Strength 10.7, Total count 812",
            "key": "natural",
            "object_types": [
                "area"
            ],
            "value": "fell"
        },
        {
            "description": "Rendered as landcover. Strength 10.6, Total count 12711",
            "key": "natural",
            "object_types": [
                "area"
            ],
            "value": "grassland"
        },
        {
            "description": "Rendered as landcover. Strength 10.6, Total count 1630",
            "key": "landuse",
            "object_types": [
                "area"
            ],
            "value": "logging"
        },
        {
            "description": "Rendered as landcover. Strength 10.2, Total count 2007",
            "key": "natural",
            "object_types": [
                "area"
            ],
            "value": "scree"
        },
        {
            "description": "Rendered as landcover. Strength 10.1, Total count 1525",
            "key": "natural",
            "object_types": [
                "area"
            ],
            "value": "beach"
        },
        {
            "description": "Rendered as landcover. Strength 10.0, Total count 12801",
            "key": "landuse",
            "object_types": [
                "area"
            ],
            "value": "orchard"
        },
        {
            "description": "Rendered as landcover. Strength 9.9, Total count 2033",
            "key": "landuse",
            "object_types": [
                "area"
            ],
            "value": "vineyard"
        },
        {
            "description": "Accepted as landcover, but not rendered. Strength: 9.9, Total count: 175",
            "key": "landuse",
            "object_types": [
                "area"
            ],
            "value": "oil_field"
        },
        {
            "description": "Rendered as landcover. Strength 9.8, Total count 843",
            "key": "natural",
            "object_types": [
                "area"
            ],
            "value": "shingle"
        },
        {
            "description": "Rendered as landcover. Strength 9.8, Total count 8362",
            "key": "landuse",
            "object_types": [
                "area"
            ],
            "value": "quarry"
        },
        {
            "description": "Rendered as landcover. Strength 9.8, Total count 1727",
            "key": "landuse",
            "object_types": [
                "area"
            ],
            "value": "farmyard"
        },
        {
            "description": "Rendered as landcover. Strength 9.7, Total count 1411",
            "key": "natural",
            "object_types": [
                "area"
            ],
            "value": "mud"
        },
        {
            "description": "Rendered as landcover. Strength 9.5, Total count 1021",
            "key": "landuse",
            "object_types": [
                "area"
            ],
            "value": "landfill"
        },
        {
            "description": "Accepted as landcover, but not rendered. Strength: 9.3, Total count: 422",
            "key": "landuse",
            "object_types": [
                "area"
            ],
            "value": "winter_sports"
        },
        {
            "description": "Rendered as landcover. Strength 9.2, Total count 52",
            "key": "natural",
            "object_types": [
                "area"
            ],
            "value": "moor"
        },
        {
            "description": "Rendered as landcover. Strength 9.1, Total count 261",
            "key": "landuse",
            "object_types": [
                "area"
            ],
            "value": "greenhouse_horticulture"
        },
        {
            "description": "Rendered as landcover. Strength 9.1, Total count 188",
            "key": "landuse",
            "object_types": [
                "area"
            ],
            "value": "paddy"
        },
        {
            "description": "Rendered as landcover. Strength 9.0, Total count 7",
            "key": "natural",
            "object_types": [
                "area"
            ],
            "value": "blockfield"
        },
        {
            "description": "Accepted as landcover, but not rendered. Strength: 9.0, Total count: 7",
            "key": "landuse",
            "object_types": [
                "area"
            ],
            "value": "wellsite"
        },
        {
            "description": "Rendered as landcover. Strength 9.0, Total count 32",
            "key": "natural",
            "object_types": [
                "area"
            ],
            "value": "bare_earth"
        },
        {
            "description": "Accepted as landcover, but not rendered. Strength: 9.0, Total count: 25",
            "key": "landuse",
            "object_types": [
                "area"
            ],
            "value": "oilfield"
        },
        {
            "description": "Accepted as landcover, but not rendered. Strength: 9.0, Total count: 23",
            "key": "landuse",
            "object_types": [
                "area"
            ],
            "value": "cultivo de ca\u00f1a"
        },
        {
            "description": "Rendered as landcover. Strength 8.9, Total count 319",
            "key": "landuse",
            "object_types": [
                "area"
            ],
            "value": "salt_pond"
        },
        {
            "description": "Accepted as landcover, but not rendered. Strength: 8.9, Total count: 69",
            "key": "landuse",
            "object_types": [
                "area"
            ],
            "value": "windfarm"
        },
        {
            "description": "Rendered as landcover. Strength 8.9, Total count 521",
            "key": "landuse",
            "object_types": [
                "area"
            ],
            "value": "allotments"
        },
        {
            "description": "Rendered as landcover. Strength 8.9, Total count 23",
            "key": "landuse",
            "object_types": [
                "area"
            ],
            "value": "peat_cutting"
        },
        {
            "description": "Accepted as landcover, but not rendered. Strength: 8.8, Total count: 28",
            "key": "landuse",
            "object_types": [
                "area"
            ],
            "value": "observatory"
        },
        {
            "description": "Accepted as landcover, but not rendered. Strength: 8.7, Total count: 144",
            "key": "landuse",
            "object_types": [
                "area"
            ],
            "value": "plant_nursery"
        },
        {
            "description": "Rendered as landcover. Strength 8.5, Total count 229",
            "key": "landuse",
            "object_types": [
                "area"
            ],
            "value": "cemetery"
        },
        {
            "description": "Accepted as landcover, but not rendered. Strength: 8.2, Total count: 310",
            "key": "landuse",
            "object_types": [
                "area"
            ],
            "value": "railway"
        },
        {
            "description": "Accepted as landcover, but not rendered. Strength: 8.1, Total count: 7",
            "key": "natural",
            "object_types": [
                "area"
            ],
            "value": "landslide"
        },
        {
            "description": "Considered to be a synonym of natural=wood",
            "key": "landuse",
            "object_types": [
                "area"
            ],
            "value": "forest"
        },
        {
            "description": "Considered to be a synonym of natural=wood",
            "key": "natural",
            "object_types": [
                "area"
            ],
            "value": "woodland"
        },
        {
            "description": "Considered to be a synonym of natural=water",
            "key": "landuse",
            "object_types": [
                "area"
            ],
            "value": "basin"
        },
        {
            "description": "Considered to be a synonym of natural=water",
            "key": "landuse",
            "object_types": [
                "area"
            ],
            "value": "reservoir"
        },
        {
            "description": "Considered to be a synonym of natural=bare_rock",
            "key": "natural",
            "object_types": [
                "area"
            ],
            "value": "bedrock"
        },
        {
            "description": "Considered to be a synonym of natural=bare_rock",
            "key": "natural",
            "object_types": [
                "area"
            ],
            "value": "lava"
        },
        {
            "description": "Considered to be a synonym of natural=sand",
            "key": "natural",
            "object_types": [
                "area"
            ],
            "value": "dune"
        },
        {
            "description": "Considered to be a synonym of natural=sand",
            "key": "natural",
            "object_types": [
                "area"
            ],
            "value": "dunes"
        },
        {
            "description": "Considered to be a synonym of natural=scrub",
            "key": "natural",
            "object_types": [
                "area"
            ],
            "value": "shrubbery"
        },
        {
            "description": "Considered to be a synonym of natural=glacier",
            "key": "natural",
            "object_types": [
                "area"
            ],
            "value": "naled"
        },
        {
            "description": "Considered to be a synonym of natural=glacier",
            "key": "natural",
            "object_types": [
                "area"
            ],
            "value": "ice"
        },
        {
            "description": "Considered to be a synonym of natural=bare_earth",
            "key": "natural",
            "object_types": [
                "area"
            ],
            "value": "ground"
        },
        {
            "description": "Considered to be a synonym of natural=grassland",
            "key": "landuse",
            "object_types": [
                "area"
            ],
            "value": "grass"
        },
        {
            "description": "Considered to be a synonym of natural=farmyard",
            "key": "landuse",
            "object_types": [
                "area"
            ],
            "value": "animal_keeping"
        },
        {
            "description": "Considered to be a synonym of built_up for the purposes of generalization",
            "key": "landuse",
            "object_types": [
                "area"
            ],
            "value": "residential"
        },
        {
            "description": "Considered to be a synonym of built_up for the purposes of generalization",
            "key": "landuse",
            "object_types": [
                "area"
            ],
            "value": "industrial"
        },
        {
            "description": "Considered to be a synonym of built_up for the purposes of generalization",
            "key": "landuse",
            "object_types": [
                "area"
            ],
            "value": "harbour"
        },
        {
            "description": "Considered to be a synonym of built_up for the purposes of generalization",
            "key": "landuse",
            "object_types": [
                "area"
            ],
            "value": "commercial"
        },
        {
            "description": "Considered to be a synonym of built_up for the purposes of generalization",
            "key": "landuse",
            "object_types": [
                "area"
            ],
            "value": "education"
        },
        {
            "description": "Considered to be a synonym of built_up for the purposes of generalization",
            "key": "landuse",
            "object_types": [
                "area"
            ],
            "value": "institutional"
        },
        {
            "description": "Considered to be a synonym of built_up for the purposes of generalization",
            "key": "landuse",
            "object_types": [
                "area"
            ],
            "value": "civic_admin"
        },
        {
            "description": "Considered to be a synonym of built_up for the purposes of generalization",
            "key": "landuse",
            "object_types": [
                "area"
            ],
            "value": "retail"
        },
        {
            "description": "Considered to be a synonym of built_up for the purposes of generalization",
            "key": "landuse",
            "object_types": [
                "area"
            ],
            "value": "garages"
        },
        {
            "description": "Considered to be a synonym of built_up for the purposes of generalization",
            "key": "landuse",
            "object_types": [
                "area"
            ],
            "value": "greenfield"
        },
        {
            "description": "Considered to be a synonym of built_up for the purposes of generalization",
            "key": "landuse",
            "object_types": [
                "area"
            ],
            "value": "construction"
        },
        {
            "description": "Considered to be a synonym of built_up for the purposes of generalization",
            "key": "landuse",
            "object_types": [
                "area"
            ],
            "value": "brownfield"
        },
        {
            "description": "Considered to be a synonym of built_up for the purposes of generalization",
            "key": "landuse",
            "object_types": [
                "area"
            ],
            "value": "village_green"
        }
    ]
}